django_ace/__init__.py
django_ace/widgets.py
django_ace/static/django_ace/widget.css
django_ace/static/django_ace/widget.js
django_ace/static/django_ace/ace/ace.js
django_ace/static/django_ace/ace/ext-beautify.js
django_ace/static/django_ace/ace/ext-code_lens.js
django_ace/static/django_ace/ace/ext-command_bar.js
django_ace/static/django_ace/ace/ext-diff.js
django_ace/static/django_ace/ace/ext-elastic_tabstops_lite.js
django_ace/static/django_ace/ace/ext-emmet.js
django_ace/static/django_ace/ace/ext-error_marker.js
django_ace/static/django_ace/ace/ext-hardwrap.js
django_ace/static/django_ace/ace/ext-inline_autocomplete.js
django_ace/static/django_ace/ace/ext-keybinding_menu.js
django_ace/static/django_ace/ace/ext-language_tools.js
django_ace/static/django_ace/ace/ext-linking.js
django_ace/static/django_ace/ace/ext-modelist.js
django_ace/static/django_ace/ace/ext-options.js
django_ace/static/django_ace/ace/ext-prompt.js
django_ace/static/django_ace/ace/ext-rtl.js
django_ace/static/django_ace/ace/ext-searchbox.js
django_ace/static/django_ace/ace/ext-settings_menu.js
django_ace/static/django_ace/ace/ext-simple_tokenizer.js
django_ace/static/django_ace/ace/ext-spellcheck.js
django_ace/static/django_ace/ace/ext-split.js
django_ace/static/django_ace/ace/ext-static_highlight.js
django_ace/static/django_ace/ace/ext-statusbar.js
django_ace/static/django_ace/ace/ext-textarea.js
django_ace/static/django_ace/ace/ext-themelist.js
django_ace/static/django_ace/ace/ext-whitespace.js
django_ace/static/django_ace/ace/keybinding-emacs.js
django_ace/static/django_ace/ace/keybinding-sublime.js
django_ace/static/django_ace/ace/keybinding-vim.js
django_ace/static/django_ace/ace/keybinding-vscode.js
django_ace/static/django_ace/ace/mode-abap.js
django_ace/static/django_ace/ace/mode-abc.js
django_ace/static/django_ace/ace/mode-actionscript.js
django_ace/static/django_ace/ace/mode-ada.js
django_ace/static/django_ace/ace/mode-alda.js
django_ace/static/django_ace/ace/mode-apache_conf.js
django_ace-1.43.3.dist-info/licenses/LICENCE
django_ace-1.43.3.dist-info/METADATA
django_ace-1.43.3.dist-info/WHEEL
django_ace-1.43.3.dist-info/top_level.txt
django_ace-1.43.3.dist-info/RECORD
