Metadata-Version: 2.4
Name: django-ace
Version: 1.43.3
Summary: django-ace provides of ACE editor with Django
Author-email: Bradley Ayers <bradley.ayers@gmail.com>, Julien Palard <julien@palard.fr>
License-Expression: BSD-2-Clause
Project-URL: Homepage, https://github.com/django-ace/django-ace
Classifier: Development Status :: 5 - Production/Stable
Classifier: Environment :: Web Environment
Classifier: Intended Audience :: Developers
Classifier: Operating System :: OS Independent
Classifier: Programming Language :: Python
Classifier: Framework :: Django
Requires-Python: >2
License-File: LICENCE
Requires-Dist: Django>=2
Dynamic: license-file
